pswitch/__init__.py
pswitch/console.py
simple_gcp_project_switcher-0.1.11.dist-info/METADATA
simple_gcp_project_switcher-0.1.11.dist-info/WHEEL
simple_gcp_project_switcher-0.1.11.dist-info/entry_points.txt
simple_gcp_project_switcher-0.1.11.dist-info/RECORD
